parquet_path_rewriter/__init__.py
parquet_path_rewriter/cli.py
parquet_path_rewriter/rewriter.py
parquet_path_rewriter-0.1.4.dist-info/METADATA
parquet_path_rewriter-0.1.4.dist-info/WHEEL
parquet_path_rewriter-0.1.4.dist-info/entry_points.txt
parquet_path_rewriter-0.1.4.dist-info/top_level.txt
parquet_path_rewriter-0.1.4.dist-info/RECORD
