Metadata-Version: 2.4
Name: parquet-path-rewriter
Version: 0.1.4
Summary: A library to rewrite relative Parquet file paths in Python code using AST manipulation.
Author-email: Rafael Sales <rafael.sales@gmail.com>
Project-URL: Homepage, https://github.com/dmux/parquet-path-rewriter
Project-URL: Bug Tracker, https://github.com/dmux/parquet-path-rewriter/issues
Keywords: ast,parquet,rewrite,refactor,pyspark,pandas
Classifier: Programming Language :: Python :: 3
Classifier: License :: OSI Approved :: MIT License
Classifier: Operating System :: OS Independent
Classifier: Topic :: Software Development :: Libraries :: Python Modules
Classifier: Topic :: Software Development :: Code Generators
Classifier: Intended Audience :: Developers
Requires-Python: >=3.9
Provides-Extra: dev
Requires-Dist: pytest>=8.3.5; extra == "dev"
Requires-Dist: pytest-cov>=6.1.1; extra == "dev"
Requires-Dist: build>=0.10; extra == "dev"
